{"kanda":3,"sarga":44,"description":"","verses":[{"v":1,"dev":"तथा तु तं समादिश्य भ्रातरं रघुनन्दनः।बबन्धासिं महातेजा जाम्बूनदमयत्सरुम्","trans":"The brilliant Rama, delight of the Raghu dynasty, thus instructed his brother and fastened a sword with a golden handle to his waist.","words":[{"d":"महातेजाः","m":"brilliant"},{"d":"रघुनन्दनः","m":"delight of the Raghu dynasty"},{"d":"भ्रातरम्","m":"brother"},{"d":"तम्","m":"to him"},{"d":"तथा","m":"in that way"},{"d":"समादिश्य","m":"instructed"},{"d":"जाम्बूनदमयत्सरुम्","m":"golden  handle"},{"d":"असिम्","m":"the sword"},{"d":"बबन्ध","m":"tied."}]},{"v":2,"dev":"तत स्त्र्यवनतं चापमादायाऽत्मविभूषणम्।आबध्य च कलापौ द्वौ जगामोदग्रविक्रमः","trans":"A man of indomitable prowess, he took the bow with three curves that was like an ornament to him, tied two quivers at the back and left.","words":[{"d":"ततः","m":"then"},{"d":"उदग्रविक्रमः","m":"of indomitable prowess"},{"d":"त्र्यवनतम्","m":"bent in three places"},{"d":"आत्मविभूषणम्","m":"an ornament to him"},{"d":"चापम्","m":"bow"},{"d":"आदाय","m":"took"},{"d":"द्वौ","m":"both"},{"d":"कलापौ","m":"two quivers"},{"d":"आबद्ध्य","m":"tied at the back"},{"d":"जगाम","m":"went."}]},{"v":3,"dev":"तं वञ्चयानो राजेन्द्रमापतन्तं निरीक्ष्यवै।बभूवान्तर्हितस्त्रासात्पुनस्सन्दर्शनेऽभवत्।।च3.44.3।।बद्धासिर्धनुरादाय प्रदुद्राव यतो मृगः।","trans":"On seeing Rama approaching him, the deer disappeared due to fear and again came within sight. With his sword and the bow, Rama chased wherever the deer ran.","words":[{"d":"आपतन्तम्","m":"approaching"},{"d":"राजेन्द्रम्","m":"to the king"},{"d":"तम्","m":"him"},{"d":"निरीक्षय","m":"seeing"},{"d":"वञ्चयानः","m":"while deceiving"},{"d":"त्रासात्","m":"out of fear"},{"d":"अन्तर्हितः","m":"disappeared"},{"d":"बभूव","m":"became"},{"d":"पुनः","m":"again"},{"d":"सन्दर्शने","m":"within sight"},{"d":"अभवत्","m":"appeared"},{"d":"बद्धासिः","m":"held his sword"},{"d":"धनुः","m":"bow"},{"d":"आदाय","m":"lifting"},{"d":"मृगः","m":"deer"},{"d":"यतः","m":"wherever"},{"d":"प्रदुद्राव","m":"ran."}]},{"v":4,"dev":"तं स्म पश्यति रूपेण द्योतमानमिवाग्रतःअवेक्ष्यावेक्ष्य धावन्तं धनुष्पाणिर्महावने।अतिवृत्तमिषोः पाताल्लोभयानं कदाचनशङ्कितन्तु समुद्भ्रान्तमुत्पतन्तमिवाम्बरे।दृश्यमानमदृश्यं च वनोद्देशेषु केषुचित्छिन्नाभ्रैरिव संवीतं शारदं चन्द्रमण्डलम्।","trans":"Rama, wielder of the bow, saw that splendid animal ahead of him. Holding the bow he saw the deer running away, bewldered into the great forest looking at him again and again. The deer was getting out of the range of his arrow, while it enticed him now and then. Suspecting that he might be caught, the deer was, as though jumping into the sky. Now it came within sight and now out of sight in the huge forest. It looked like the autumnal moon surrounded by clouds. (The clouds muffle the Moon and reveal him now and then).","words":[{"d":"धनुष्पाणिः","m":"wielder of the bow (Rama)"},{"d":"अवेक्ष्य","m":"saw"},{"d":"महावने","m":"in the huge forest"},{"d":"धावन्तम्","m":"running"},{"d":"तम्","m":"him"},{"d":"रूपेण","m":"form"},{"d":"अग्रतः","m":"in front"},{"d":"पश्यति स्म","m":"saw"},{"d":"कदाचन","m":"sometimes"},{"d":"इषोः","m":"scared of the arrow"},{"d":"पातात्","m":"ran"},{"d":"अतिवृत्तम्","m":"went out of reach"},{"d":"लोभयानम्","m":"enticing"},{"d":"शङ्कितम्","m":"frightened"},{"d":"समुद्भ्रान्तम्","m":"bewildered"},{"d":"अम्बरे","m":"in the sky"},{"d":"उत्पतन्तमिव","m":"as if flying  up"},{"d":"छिन्नाभ्रैः","m":"by the scattered clouds"},{"d":"संवीतम्","m":"surrounded"},{"d":"शारदम्","m":"autumnal,चन्द्रमण्डलम् इव like the orb of the Moon"},{"d":"केषुचित्","m":"in certain places"},{"d":"वनोद्देशेषु","m":"in the forest tract"},{"d":"दृश्यमानम्","m":"came within sight"},{"d":"अदृश्यं च","m":"again disappeared."}]},{"v":5,"dev":"तं स्म पश्यति रूपेण द्योतमानमिवाग्रतःअवेक्ष्यावेक्ष्य धावन्तं धनुष्पाणिर्महावने।अतिवृत्तमिषोः पाताल्लोभयानं कदाचनशङ्कितन्तु समुद्भ्रान्तमुत्पतन्तमिवाम्बरे।दृश्यमानमदृश्यं च वनोद्देशेषु केषुचित्छिन्नाभ्रैरिव संवीतं शारदं चन्द्रमण्डलम्।","trans":"Rama, wielder of the bow, saw that splendid animal ahead of him. Holding the bow he saw the deer running away, bewldered into the great forest looking at him again and again. The deer was getting out of the range of his arrow, while it enticed him now and then. Suspecting that he might be caught, the deer was, as though jumping into the sky. Now it came within sight and now out of sight in the huge forest. It looked like the autumnal moon surrounded by clouds. (The clouds muffle the Moon and reveal him now and then).","words":[{"d":"धनुष्पाणिः","m":"wielder of the bow (Rama)"},{"d":"अवेक्ष्य","m":"saw"},{"d":"महावने","m":"in the huge forest"},{"d":"धावन्तम्","m":"running"},{"d":"तम्","m":"him"},{"d":"रूपेण","m":"form"},{"d":"अग्रतः","m":"in front"},{"d":"पश्यति स्म","m":"saw"},{"d":"कदाचन","m":"sometimes"},{"d":"इषोः","m":"scared of the arrow"},{"d":"पातात्","m":"ran"},{"d":"अतिवृत्तम्","m":"went out of reach"},{"d":"लोभयानम्","m":"enticing"},{"d":"शङ्कितम्","m":"frightened"},{"d":"समुद्भ्रान्तम्","m":"bewildered"},{"d":"अम्बरे","m":"in the sky"},{"d":"उत्पतन्तमिव","m":"as if flying  up"},{"d":"छिन्नाभ्रैः","m":"by the scattered clouds"},{"d":"संवीतम्","m":"surrounded"},{"d":"शारदम्","m":"autumnal,चन्द्रमण्डलम् इव like the orb of the Moon"},{"d":"केषुचित्","m":"in certain places"},{"d":"वनोद्देशेषु","m":"in the forest tract"},{"d":"दृश्यमानम्","m":"came within sight"},{"d":"अदृश्यं च","m":"again disappeared."}]},{"v":6,"dev":"तं स्म पश्यति रूपेण द्योतमानमिवाग्रतःअवेक्ष्यावेक्ष्य धावन्तं धनुष्पाणिर्महावने।अतिवृत्तमिषोः पाताल्लोभयानं कदाचनशङ्कितन्तु समुद्भ्रान्तमुत्पतन्तमिवाम्बरे।दृश्यमानमदृश्यं च वनोद्देशेषु केषुचित्छिन्नाभ्रैरिव संवीतं शारदं चन्द्रमण्डलम्।","trans":"Rama, wielder of the bow, saw that splendid animal ahead of him. Holding the bow he saw the deer running away, bewldered into the great forest looking at him again and again. The deer was getting out of the range of his arrow, while it enticed him now and then. Suspecting that he might be caught, the deer was, as though jumping into the sky. Now it came within sight and now out of sight in the huge forest. It looked like the autumnal moon surrounded by clouds. (The clouds muffle the Moon and reveal him now and then).","words":[{"d":"धनुष्पाणिः","m":"wielder of the bow (Rama)"},{"d":"अवेक्ष्य","m":"saw"},{"d":"महावने","m":"in the huge forest"},{"d":"धावन्तम्","m":"running"},{"d":"तम्","m":"him"},{"d":"रूपेण","m":"form"},{"d":"अग्रतः","m":"in front"},{"d":"पश्यति स्म","m":"saw"},{"d":"कदाचन","m":"sometimes"},{"d":"इषोः","m":"scared of the arrow"},{"d":"पातात्","m":"ran"},{"d":"अतिवृत्तम्","m":"went out of reach"},{"d":"लोभयानम्","m":"enticing"},{"d":"शङ्कितम्","m":"frightened"},{"d":"समुद्भ्रान्तम्","m":"bewildered"},{"d":"अम्बरे","m":"in the sky"},{"d":"उत्पतन्तमिव","m":"as if flying  up"},{"d":"छिन्नाभ्रैः","m":"by the scattered clouds"},{"d":"संवीतम्","m":"surrounded"},{"d":"शारदम्","m":"autumnal,चन्द्रमण्डलम् इव like the orb of the Moon"},{"d":"केषुचित्","m":"in certain places"},{"d":"वनोद्देशेषु","m":"in the forest tract"},{"d":"दृश्यमानम्","m":"came within sight"},{"d":"अदृश्यं च","m":"again disappeared."}]},{"v":7,"dev":"मुहुर्तादेव ददृशे मुहुर्दूरात्प्रकाशतेदर्शनादर्शनादेवं सोऽपाकर्षत राघवम्।सुदूरमाश्रमस्यास्य मारीचो मृगतां गतः","trans":"Maricha, transformed into a deer, was seen now near, now faroff. He pulled Rama away from the hermitage through his exits and entrances.","words":[{"d":"मृगताम्","m":"in the form of a deer"},{"d":"गतः","m":"transformed"},{"d":"सः मारीचः","m":"that Maricha"},{"d":"मुहूर्तादेव","m":"for a moment"},{"d":"ददृशे","m":"was seen"},{"d":"मुहुः","m":"again, (मुहूर्तात् another moment)"},{"d":"दूरात्","m":"at a distance"},{"d":"प्रकाशते","m":"appeared"},{"d":"एवं","m":"as"},{"d":"दर्शनादर्शनात्","m":"appearing and disappearing"},{"d":"राघवम्","m":"Rama"},{"d":"उपाकर्षत","m":"pulled away."}]},{"v":8,"dev":"मुहुर्तादेव ददृशे मुहुर्दूरात्प्रकाशतेदर्शनादर्शनादेवं सोऽपाकर्षत राघवम्।सुदूरमाश्रमस्यास्य मारीचो मृगतां गतः","trans":"Maricha, transformed into a deer, was seen now near, now faroff. He pulled Rama away from the hermitage through his exits and entrances.","words":[{"d":"मृगताम्","m":"in the form of a deer"},{"d":"गतः","m":"transformed"},{"d":"सः मारीचः","m":"that Maricha"},{"d":"मुहूर्तादेव","m":"for a moment"},{"d":"ददृशे","m":"was seen"},{"d":"मुहुः","m":"again, (मुहूर्तात् another moment)"},{"d":"दूरात्","m":"at a distance"},{"d":"प्रकाशते","m":"appeared"},{"d":"एवं","m":"as"},{"d":"दर्शनादर्शनात्","m":"appearing and disappearing"},{"d":"राघवम्","m":"Rama"},{"d":"उपाकर्षत","m":"pulled away."}]},{"v":9,"dev":"आसीत् क्रुद्धस्तु काकुत्स्थो विवशस्तेन मोहितः।अथावतस्थे संभ्रान्तश्चायामाश्रित्य शाद्वले","trans":"Deluded by that deer, Rama got tired, perplexed and angry. Then bewidered, he waited on a grassland under a shade.","words":[{"d":"तेन","m":"by that"},{"d":"मोहितः","m":"deluded"},{"d":"विवशः","m":"tired"},{"d":"क्रुद्धः","m":"in rage"},{"d":"आसीत्","m":"was"},{"d":"अथ","m":"then"},{"d":"संभ्रान्तः","m":"perplexed"},{"d":"छायाम्","m":"shade"},{"d":"आश्रित्य","m":"seeking"},{"d":"शाद्वले","m":"on green grass"},{"d":"अवतस्थे","m":"waited."}]},{"v":10,"dev":"स तमुन्मादयामास मृगरूपो निशाचरः।मृगैः परिवृतो वन्यैरदूरात्प्रत्यदृश्यत","trans":"That demon transformed himself into a deer and, surrounded by the animals of the forest at close range, attracted his attention.","words":[{"d":"मृगरूपः","m":"assuming the form of a deer"},{"d":"सः निशाचरः","m":"that demon"},{"d":"तम्","m":"him"},{"d":"उन्मादयामास","m":"excited"},{"d":"वन्यैः","m":"with forest"},{"d":"मृगैः","m":"animals"},{"d":"परिवृतः","m":"surrounded by"},{"d":"अदूरात्","m":"not very far from him"},{"d":"अदृश्यत","m":"was seen."}]},{"v":11,"dev":"गृहीतुकामं दृष्ट्वैवं पुनरेवाभ्यधावत।तत्क्षणादेव संत्रासात्पुनरन्तर्हितोऽभवत्","trans":"Seeing Rama's intention to catch him, the deer ran away once again out of fear and disappeared in a moment.","words":[{"d":"गृहीतुकामम्","m":"intending to catch him"},{"d":"एवम्","m":"in that way"},{"d":"दृष्ट्वा","m":"after seeing"},{"d":"पुनरेव","m":"once again"},{"d":"अभ्यधावत","m":"ran"},{"d":"तत्क्षणादेव","m":"in a moment"},{"d":"पुनरेव","m":"again"},{"d":"त्रासात्","m":"out of fear"},{"d":"अन्तर्हितः","m":"disappeared"},{"d":"अभवत्","m":"became."}]},{"v":12,"dev":"पुनरेव ततो दूराद्वृक्षषण्डाद्विनिस्सृतम्।दृष्ट्वा रामो महातेजास्तं हन्तुं कृतनिश्चयः","trans":"Resplendent Rama saw the deer coming out of a cluster of trees at a distance and determined to kill him.","words":[{"d":"ततः","m":"then"},{"d":"महातेजाः","m":"resplendent"},{"d":"रामः","m":"Rama"},{"d":"पुनरेव","m":"again"},{"d":"दूरात्","m":"from a distance"},{"d":"वृक्षषण्डात्","m":"from a group of trees"},{"d":"विनिस्सृतम्","m":"coming out"},{"d":"तम्","m":"him"},{"d":"दृष्ट्वा","m":"saw"},{"d":"हन्तुम्","m":"to kill"},{"d":"कृतनिश्चयः","m":"determined ."}]},{"v":13,"dev":"भूयस्तु शरमुद्धृत्य कुपितस्तत्र राघवः।सूर्यरश्मिप्रतीकाशं ज्वलन्तमरिमर्दनःसन्धाय सुदृढे चापे विकृष्य बलवद्बली।तमेव मृगमुद्दिश्य श्वसन्तमिव पन्नगम्मुमोच ज्वलितं दीप्तमस्त्रं ब्रह्मविनिर्मितम्।","trans":"Powerful Rama, destroyer of foes, lifted in a rage his arrow blazing like the light of the Sun, strung it to his sturdy bow and drew it with all his force. He then aimed at the deer and released the shining arrow created by Brahma which went hissing like a serpent.","words":[{"d":"तत्र","m":"there"},{"d":"भूयः","m":"again"},{"d":"कुपितः","m":"enraged"},{"d":"अरिमर्दनः","m":"destroyer of foes"},{"d":"बली","m":"powerful,राघवः Rama"},{"d":"सूर्यरश्मिप्रतीकाशम्","m":"glowing like the rays of the Sun"},{"d":"ज्वलन्तम्","m":"blazing"},{"d":"शरम्","m":"dart"},{"d":"उद्धृत्य","m":"lifting"},{"d":"सुदृढे","m":"in a sturdy"},{"d":"चापे","m":"in bow"},{"d":"सन्धाय","m":"aiming"},{"d":"बलवत्","m":"with force"},{"d":"विकृष्य","m":"drew"},{"d":"श्वसन्तम्","m":"sighing"},{"d":"पन्नगम् इव","m":"like the serpent"},{"d":"ज्वलितम्","m":"burning"},{"d":"दीप्तम्","m":"shining"},{"d":"ब्रह्मनिर्मितम्","m":"created by Brahma"},{"d":"अस्त्रम्","m":"weapon"},{"d":"तम्","m":"him"},{"d":"मृगमेव","m":"on the deer"},{"d":"उद्दिश्य","m":"aiming"},{"d":"मुमोच","m":"released."}]},{"v":14,"dev":"भूयस्तु शरमुद्धृत्य कुपितस्तत्र राघवः।सूर्यरश्मिप्रतीकाशं ज्वलन्तमरिमर्दनःसन्धाय सुदृढे चापे विकृष्य बलवद्बली।तमेव मृगमुद्दिश्य श्वसन्तमिव पन्नगम्मुमोच ज्वलितं दीप्तमस्त्रं ब्रह्मविनिर्मितम्।","trans":"Powerful Rama, destroyer of foes, lifted in a rage his arrow blazing like the light of the Sun, strung it to his sturdy bow and drew it with all his force. He then aimed at the deer and released the shining arrow created by Brahma which went hissing like a serpent.","words":[{"d":"तत्र","m":"there"},{"d":"भूयः","m":"again"},{"d":"कुपितः","m":"enraged"},{"d":"अरिमर्दनः","m":"destroyer of foes"},{"d":"बली","m":"powerful,राघवः Rama"},{"d":"सूर्यरश्मिप्रतीकाशम्","m":"glowing like the rays of the Sun"},{"d":"ज्वलन्तम्","m":"blazing"},{"d":"शरम्","m":"dart"},{"d":"उद्धृत्य","m":"lifting"},{"d":"सुदृढे","m":"in a sturdy"},{"d":"चापे","m":"in bow"},{"d":"सन्धाय","m":"aiming"},{"d":"बलवत्","m":"with force"},{"d":"विकृष्य","m":"drew"},{"d":"श्वसन्तम्","m":"sighing"},{"d":"पन्नगम् इव","m":"like the serpent"},{"d":"ज्वलितम्","m":"burning"},{"d":"दीप्तम्","m":"shining"},{"d":"ब्रह्मनिर्मितम्","m":"created by Brahma"},{"d":"अस्त्रम्","m":"weapon"},{"d":"तम्","m":"him"},{"d":"मृगमेव","m":"on the deer"},{"d":"उद्दिश्य","m":"aiming"},{"d":"मुमोच","m":"released."}]},{"v":15,"dev":"शरीरं मृगरूपस्य विनिर्भिद्य शरोत्तमःमारीचस्यैव हृदयं बिभेदाशनिसन्निभः।","trans":"The great arrow which was like a thunderbolt first pierced into the body of Maricha who had assumed the form of a deer and then tore his heart.","words":[{"d":"आशनिसन्निभः","m":"like thunderbolt"},{"d":"शरोत्तमः","m":"the great arrow"},{"d":"मृगरूपस्य","m":"assuming deer form"},{"d":"शरीरम्","m":"body"},{"d":"विनिर्भिद्य","m":"pierced"},{"d":"मारीचस्य","m":"Maricha's"},{"d":"हृदयमेव","m":"heart"},{"d":"बिभेद","m":"tore."}]},{"v":16,"dev":"तालमात्रमथोत्प्लुत्य न्यपतत्सशरातुरःविनदन्भैरवं नादं धरण्यामल्पजीवितः।","trans":"And, hurt by the dart, Maricha roared frighteningly, leaped as high as a palm tree and dropped down on earth almost dead.","words":[{"d":"अथ","m":"and then"},{"d":"सः","m":"Maricha"},{"d":"शरातुरः","m":"hurt by the dart"},{"d":"अल्पजीवितः","m":"very little life left"},{"d":"भैरवं नादम्","m":"frightening sound"},{"d":"विनदन्","m":"released"},{"d":"तालमात्रम्","m":"to the height of a palm tree"},{"d":"उत्प्लुत्य","m":"leaped up"},{"d":"धरण्याम्","m":"on earth"},{"d":"न्यपतत्","m":"dropped."}]},{"v":17,"dev":"म्रियमाणस्तु मारीचो जहौ तां कृत्रिमां तनुम्स्मृत्वा तद्वचनं रक्षो दध्यौ केन तु लक्ष्मणम्।इह प्रस्थापयेत्सीता शून्ये तां रावणो हरेत्","trans":"Maricha gave up his false form of the deer and before breathing his last, remembered the words of Ravana. He thought over the means through which Sita could send Lakshmana to this spot so that Ravana would abduct her when she is alone.","words":[{"d":"मारीचः","m":"Maricha"},{"d":"म्रियमाणः","m":"breathing his last"},{"d":"कृत्रिमाम्","m":"artificial"},{"d":"ताम्","m":"that"},{"d":"तनुम्","m":"body"},{"d":"जहौ","m":"gave up"},{"d":"रक्षः","m":"the demon"},{"d":"तद्वचनम्","m":"those words"},{"d":"स्मृत्वा","m":"remembering"},{"d":"दध्यौ","m":"thought"},{"d":"सीता","m":"Sita"},{"d":"केन","m":"by what means"},{"d":"लक्ष्मणम्","m":"Lakshmana"},{"d":"इह","m":"here"},{"d":"प्रस्थापयेत्","m":"she may send"},{"d":"शून्ये","m":"in seclusion"},{"d":"ताम्","m":"her"},{"d":"रावणः","m":"Ravana"},{"d":"हरेत्","m":"will abduct."}]},{"v":18,"dev":"म्रियमाणस्तु मारीचो जहौ तां कृत्रिमां तनुम्स्मृत्वा तद्वचनं रक्षो दध्यौ केन तु लक्ष्मणम्।इह प्रस्थापयेत्सीता शून्ये तां रावणो हरेत्","trans":"Maricha gave up his false form of the deer and before breathing his last, remembered the words of Ravana. He thought over the means through which Sita could send Lakshmana to this spot so that Ravana would abduct her when she is alone.","words":[{"d":"मारीचः","m":"Maricha"},{"d":"म्रियमाणः","m":"breathing his last"},{"d":"कृत्रिमाम्","m":"artificial"},{"d":"ताम्","m":"that"},{"d":"तनुम्","m":"body"},{"d":"जहौ","m":"gave up"},{"d":"रक्षः","m":"the demon"},{"d":"तद्वचनम्","m":"those words"},{"d":"स्मृत्वा","m":"remembering"},{"d":"दध्यौ","m":"thought"},{"d":"सीता","m":"Sita"},{"d":"केन","m":"by what means"},{"d":"लक्ष्मणम्","m":"Lakshmana"},{"d":"इह","m":"here"},{"d":"प्रस्थापयेत्","m":"she may send"},{"d":"शून्ये","m":"in seclusion"},{"d":"ताम्","m":"her"},{"d":"रावणः","m":"Ravana"},{"d":"हरेत्","m":"will abduct."}]},{"v":19,"dev":"स प्राप्तकालमाज्ञाय चकार च तत स्वनम्।सदृशं राघवस्येह हा सीते लक्ष्मणेति च","trans":"Then Maricha realised that the appropriate time had come. In a voice similar to Rama's, he shouted loudly 'Alas Sita, Alas Lakshmana '","words":[{"d":"ततः","m":"then"},{"d":"सः","m":"Maricha"},{"d":"प्राप्तकालम्","m":"the right time"},{"d":"आज्ञाय","m":"having realised"},{"d":"राघवस्य","m":"Rama's"},{"d":"सदृशम्","m":"similar"},{"d":"हा सीते","m":"Alas, Sita"},{"d":"लक्ष्मण","m":"Lakshmana"},{"d":"इति च","m":"like that"},{"d":"स्वनम्","m":"a sound"},{"d":"चकार","m":"released."}]},{"v":20,"dev":"तेन मर्मणि निर्विद्धं शरेणानुपमेन हि।मृगरूपं तु तत्त्यक्त्वा राक्षसं रूपमास्थितःचक्रे स सुमहाकायं मारीचो जीवितं त्यजन्।","trans":"Struck in the vital part by Rama's matchless dart, Maricha gave up the form of the deer and assumed his huge body of the demon.","words":[{"d":"सः मारीचः","m":"that, Maricha"},{"d":"तेन","m":"by that"},{"d":"अनुपमेन","m":"matchless"},{"d":"शरेण","m":"by  the dart"},{"d":"मर्मणि","m":"in vital part"},{"d":"निर्विद्धम्","m":"struck"},{"d":"तत्","m":"then"},{"d":"मृगरूपम्","m":"form of a deer"},{"d":"त्वक्त्वा","m":"giving up"},{"d":"राक्षसं रूपम्","m":"form of a demon"},{"d":"आस्थितः","m":"assumed"},{"d":"जीवितम्","m":"life"},{"d":"त्यजन्","m":"while giving up"},{"d":"सुमहाकायम्","m":"that huge body"},{"d":"चक्रे","m":"attained."}]},{"v":21,"dev":"तं दृष्ट्वा पतितं भूमौ राक्षसं घोरदर्शनम्रामो रुधिरसिक्ताङ्गं चेष्टमानं महीतले।जगाम मनसा सीतां लक्ष्मणस्य वचस्स्मरन्","trans":"Seeing that terrific demon fallen on the ground, drenched in blood, and strring his limbs, Rama thought of Lakshmana's words and reached Sita mentally (thought of her).","words":[{"d":"रामः","m":"Rama"},{"d":"भूमौ","m":"on the ground"},{"d":"पतितम्","m":"fallen down"},{"d":"घोरदर्शनम्","m":"terrific figure"},{"d":"रुधिरसिक्ताङ्गम्","m":"drenched in blood"},{"d":"महीतले","m":"on the ground"},{"d":"चेष्टमानम्","m":"moving his limbs"},{"d":"तं राक्षसम्","m":"that demon"},{"d":"दृष्ट्वा","m":"seen"},{"d":"लक्ष्मणस्य","m":"Lakshmana's"},{"d":"वचः","m":"words"},{"d":"स्मरन्","m":"remembered"},{"d":"मनसा","m":"by his mind"},{"d":"सीताम्","m":"Sita"},{"d":"जगाम","m":"went."}]},{"v":22,"dev":"तं दृष्ट्वा पतितं भूमौ राक्षसं घोरदर्शनम्रामो रुधिरसिक्ताङ्गं चेष्टमानं महीतले।जगाम मनसा सीतां लक्ष्मणस्य वचस्स्मरन्","trans":"Seeing that terrific demon fallen on the ground, drenched in blood, and strring his limbs, Rama thought of Lakshmana's words and reached Sita mentally (thought of her).","words":[{"d":"रामः","m":"Rama"},{"d":"भूमौ","m":"on the ground"},{"d":"पतितम्","m":"fallen down"},{"d":"घोरदर्शनम्","m":"terrific figure"},{"d":"रुधिरसिक्ताङ्गम्","m":"drenched in blood"},{"d":"महीतले","m":"on the ground"},{"d":"चेष्टमानम्","m":"moving his limbs"},{"d":"तं राक्षसम्","m":"that demon"},{"d":"दृष्ट्वा","m":"seen"},{"d":"लक्ष्मणस्य","m":"Lakshmana's"},{"d":"वचः","m":"words"},{"d":"स्मरन्","m":"remembered"},{"d":"मनसा","m":"by his mind"},{"d":"सीताम्","m":"Sita"},{"d":"जगाम","m":"went."}]},{"v":23,"dev":"मारीचस्य तु मायैषा पूर्वोक्तं लक्ष्मणेन तु।तत्तथा ह्यभवच्चाद्य मारीचोऽयं मया हतः","trans":"This is an illusion created by Maricha. It happened exactly the way Lakshmana had said earlier. Maricha is now killed.","words":[{"d":"एषा","m":"this way"},{"d":"मारीचस्य","m":"Maricha's"},{"d":"माया","m":"magic"},{"d":"लक्ष्मणेन","m":"by Lakshmana"},{"d":"पूर्वोक्तम्","m":"told earlier"},{"d":"तत्","m":"that"},{"d":"तथा","m":"in the same way"},{"d":"अभवत् हि","m":"it happened"},{"d":"मया","m":"by me"},{"d":"हतः","m":"killed"},{"d":"अयम्","m":"that"},{"d":"मारीचः","m":"Maricha."}]},{"v":24,"dev":"हा सीते लक्ष्मणेत्येवमाक्रुश्य च महास्वरम्।ममार राक्षसस्सोऽयं श्रुत्वा सीता कथं भवेत्लक्ष्मणश्च महाबाहुः कामवस्थां गमिष्यति।इति सञ्चिन्त्य धर्मात्मा रामो हृष्टतनूरुहः","trans":"This demon Maricha screamed aloud saying, 'Alas, Sita, Alas, Lakshmana'. He is now dead. How would Sita react to this voice? What would be the condition of Lakshmana? While righteous Rama reflected on this, his hair stood on end.","words":[{"d":"सः","m":"he, Maricha"},{"d":"अयं राक्षसः","m":"this demon"},{"d":"हा सीते","m":"Alas, Sita"},{"d":"इत्येवम्","m":"in this manner"},{"d":"महास्वरम्","m":"loudly"},{"d":"आक्रुश्य","m":"screamed"},{"d":"ममार","m":"died"},{"d":"श्रुत्वा","m":"heard"},{"d":"सीता","m":"Sita"},{"d":"कथम्","m":"how"},{"d":"भवेत्","m":"will she be"},{"d":"महाबाहुः","m":"long armed"},{"d":"लक्ष्मणश्च","m":"Lakshmana too"},{"d":"काम्","m":"what"},{"d":"अवस्थाम्","m":"situation"},{"d":"गमिष्यति","m":"will reach"},{"d":"धर्मात्मा","m":"righteous"},{"d":"रामः","m":"Rama"},{"d":"इति","m":"like this"},{"d":"सञ्चिन्त्य","m":"on thinking"},{"d":"हृष्टतनूरूहः","m":"his hair stood on end."}]},{"v":25,"dev":"हा सीते लक्ष्मणेत्येवमाक्रुश्य च महास्वरम्।ममार राक्षसस्सोऽयं श्रुत्वा सीता कथं भवेत्लक्ष्मणश्च महाबाहुः कामवस्थां गमिष्यति।इति सञ्चिन्त्य धर्मात्मा रामो हृष्टतनूरुहः","trans":"This demon Maricha screamed aloud saying, 'Alas, Sita, Alas, Lakshmana'. He is now dead. How would Sita react to this voice? What would be the condition of Lakshmana? While righteous Rama reflected on this, his hair stood on end.","words":[{"d":"सः","m":"he, Maricha"},{"d":"अयं राक्षसः","m":"this demon"},{"d":"हा सीते","m":"Alas, Sita"},{"d":"इत्येवम्","m":"in this manner"},{"d":"महास्वरम्","m":"loudly"},{"d":"आक्रुश्य","m":"screamed"},{"d":"ममार","m":"died"},{"d":"श्रुत्वा","m":"heard"},{"d":"सीता","m":"Sita"},{"d":"कथम्","m":"how"},{"d":"भवेत्","m":"will she be"},{"d":"महाबाहुः","m":"long armed"},{"d":"लक्ष्मणश्च","m":"Lakshmana too"},{"d":"काम्","m":"what"},{"d":"अवस्थाम्","m":"situation"},{"d":"गमिष्यति","m":"will reach"},{"d":"धर्मात्मा","m":"righteous"},{"d":"रामः","m":"Rama"},{"d":"इति","m":"like this"},{"d":"सञ्चिन्त्य","m":"on thinking"},{"d":"हृष्टतनूरूहः","m":"his hair stood on end."}]},{"v":26,"dev":"तत्र रामं भयं तीव्रमाविवेश विषादजम्।राक्षसं मृगरूपं तं हत्वा श्रुत्वा च तत्स्वरम्","trans":"After killing the demon in the figure of a deer and hearing his voice, Rama was overtaken by intense fear born of despair.","words":[{"d":"मृगरूपम्","m":"in the form of a deer"},{"d":"राक्षसम्","m":"demon"},{"d":"हत्वा","m":"having killed"},{"d":"तत्स्वरम्","m":"that sound"},{"d":"श्रुत्वा च","m":"having heard"},{"d":"तत्र","m":"there"},{"d":"रामम्","m":"Rama"},{"d":"विषादजम्","m":"born of sadness"},{"d":"तीव्रम्","m":"intense"},{"d":"भयम्","m":"fear"},{"d":"आविवेश","m":"came over."}]},{"v":27,"dev":"निहत्य पृषतं चान्यं मांसमादाय राघवः।त्वरमाणो जनस्थानं ससाराभिमुखस्तदा","trans":"Then Rama killed another deer, collected the venison and hastened to Janasthana. इत्यार्षे श्रीमद्रामायणे वाल्मीकीय आदिकाव्ये अरण्यकाण्डे चतुश्चत्वारिंशस्सर्गः। Thus ends the fortyfourth sarga of Aranyakanda of the holy Ramayana the first epic composed by sage Valmiki.","words":[{"d":"तदा","m":"then"},{"d":"राघवः","m":"Rama"},{"d":"अन्यम्","m":"another"},{"d":"पृषतम्","m":"deer"},{"d":"निहत्य","m":"having killed"},{"d":"मांसम्","m":"venison"},{"d":"आदाय","m":"collected"},{"d":"त्वरमाणः","m":"quickly"},{"d":"जनस्थानम्","m":"Janasthanam"},{"d":"अभिमुखः","m":"towards"},{"d":"ससार","m":"departed."}]}]}