{"kanda":6,"sarga":66,"description":"","verses":[{"v":1,"dev":"स लङ्घयित्वाप्राकारंगिरिकूटोपमोमहान् ।निर्ययौनगरात्तूर्णंकुम्भकर्णोमहाबलः","trans":"Mighty Kumbhakarna, a gigantic one, resembling a mountain peak, having swiftly crossed over the boundary of the city roared.","words":[{"d":"गिरिकूटोपमः","m":"who resembled peak of mountain"},{"d":"महान्","m":"gigantic"},{"d":"महाबलः","m":"mighty"},{"d":"सःकुम्भकर्ण:","m":"Kumbhakarna"},{"d":"प्राकारं","m":"boundary"},{"d":"लङ्घयित्वा","m":"having crossed"},{"d":"तूर्णम्","m":"swiftly"},{"d":"नगरात्","m":"from the city"},{"d":"निर्ययौ","m":"roared."}]},{"v":2,"dev":"ननाद च महानादंसमुद्रमभिनादयन् ।विजयन्निवनिर्घातन्विधमन्निवपर्वतान्","trans":"Kumbhakarna roared making loud noises as if proclaiming victory, like the breaking of mountains and reverberating of ocean.","words":[{"d":"निर्घातान्","m":"bringing out loud noise,विजयत्रि as if proclaiming victory"},{"d":"पर्वतान्","m":"mountains"},{"d":"विधमन् इव","m":"like breaking"},{"d":"महानादम्","m":"great sound"},{"d":"समुद्रम्","m":"ocean"},{"d":"अभिनादयन्","m":"reverberate"},{"d":"नादयन","m":"roared."}]},{"v":3,"dev":"तमवध्यंमघवतायमेनवरुणेनवा ।प्रेक्ष्यभीमाक्षमायान्तंवानराविप्रदुद्रुवुः","trans":"Observing that rakshasa with frightening eyes, who could not be killed by Indra or Yama or even by Varuna coming towards them the vanaras ran in fear.","words":[{"d":"मघवता","m":"by Indra"},{"d":"वरुणेनवा","m":"or even Varuna"},{"d":"अवध्यम्","m":"not be killed"},{"d":"भीमाक्षम्","m":"with frightening eyes"},{"d":"तम्","m":"him"},{"d":"प्रेक्ष्य","m":"observing"},{"d":"वानराः","m":"the Vanaras"},{"d":"विप्रदुद्रुवुः","m":"ran in fear."}]},{"v":4,"dev":"तांस्तुविप्रद्रुतान् दृष्टवाराजपुत्रोऽङ्गदोऽब्रवीत् ।नलंनीलंगवाक्षं च कुमुदं च महाबलम्","trans":"Seeing the Vanaras running in fear, Angada spoke to Nala, Nila, Gavaksha, Mahabala and Kumuda.","words":[{"d":"विप्रद्रुतान्","m":"running in fear"},{"d":"तान्","m":"them"},{"d":"नलम्","m":"Nala"},{"d":"नीलम्","m":"Nila"},{"d":"गवाक्षं च","m":"and Gavaksha"},{"d":"महाबलम्","m":"Mahabala"},{"d":"कुमुदम्","m":"Kumuda"},{"d":"दृष्टवा","m":"seeing"},{"d":"राजपुत्रः","m":"prince"},{"d":"अब्रवीत्","m":"spoke"}]},{"v":5,"dev":"आत्मानमत्रविस्मृत्यवीर्याण्यभिजनानि च ।क्वगच्छतभयत्रस्ताःप्राकृताहरयोयथा","trans":"\"Forgetting yourself, that you are warriors, not knowing by nature, being Vanaras where are you going?\"","words":[{"d":"आत्मानम्","m":"yourself"},{"d":"अत्र","m":"there"},{"d":"वीर्याणि","m":"warriors"},{"d":"अभिजनानि च","m":"not knowing"},{"d":"विस्मृत्य","m":"forgetting"},{"d":"प्राकृताः","m":"by nature"},{"d":"हरयःयथा","m":"like the Vanaras"},{"d":"भयत्रस्ताः","m":"fearing"},{"d":"क्व","m":"where"},{"d":"गच्छत","m":"are you going."}]},{"v":6,"dev":"साधुसौम्या निवर्तध्वंकिप्राणान्परिरक्षथ ।नालंयुद्धायवैरक्षोमहतीयंबिभीषका","trans":"\"O good Vanaras! You are modest. Return. Why are you protecting your life? This Rakshasa is not capable of facing war. He can create only fear.\"","words":[{"d":"सौम्याः","m":"good"},{"d":"साधु","m":"modest"},{"d":"निवर्तध्वम्","m":"return"},{"d":"प्राणान्","m":"life"},{"d":"किम्","m":"why"},{"d":"परिरक्षथ","m":"protecting"},{"d":"रक्षः","m":"Rakshasa"},{"d":"युद्धाय","m":"in war"},{"d":"नालम्","m":"not capable facing"},{"d":"इयम्","m":"this"},{"d":"महती","m":"great"},{"d":"बिभीषिका","m":"who can create fear."}]},{"v":7,"dev":"महतीमुथतितामेनांराक्षसानांबिभीषिकाम् ।विक्रमाद्विधमिष्यामोनिवर्तध्वंप्लवङ्गमाः","trans":"\"O Vanaras! We will dispel this huge rakshasa, a nightmare with our power. Come back.\"","words":[{"d":"प्लवङ्गमाः","m":"Vanaras"},{"d":"राक्षसानाम्","m":"Rakshasas"},{"d":"उथतिताम्","m":"dispel"},{"d":"महतीम्","m":"huge"},{"d":"एनांबिभीषिकाम्","m":"this nightmare"},{"d":"विक्रमात्","m":"with our power"},{"d":"विधमिष्यामः","m":"kill them"},{"d":"निवर्तध्वम्","m":"come back."}]},{"v":8,"dev":"कृच्छ्रेणतुसमाश्वस्यसङ्गम्य च ततस्ततः ।वृक्षाद्रिहस्ताहरयस्सम्प्रतस्थूरणाजिरम्","trans":"Overcoming fear, the Vanaras getting together from here and there holding trees by hand, proceeded to the battlefield.","words":[{"d":"हरयः","m":"Vanaras"},{"d":"कृच्छ्रेण","m":"from distress"},{"d":"समाश्वस्य","m":"getting over fear"},{"d":"ततस्ततः","m":"from here and there"},{"d":"सङ्गम्य","m":"getting together"},{"d":"वृक्षान्","m":"trees"},{"d":"हस्ता","m":"by hand"},{"d":"रणाजिरम्","m":"to battlefield"},{"d":"सम्प्रतस्थुः","m":"proceeded."}]},{"v":9,"dev":"तेनिवृत्यतुसङ्कृद्धाःकुम्भकर्णंवनौकसः ।निर्जघ्नुःपरमक्रुद्धास्समदाइवकुञ्जराः","trans":"Those forest rangers who were extremely enraged turned back to hit, determined like the elephants in rut went to vanquish Kumbhakarna.","words":[{"d":"ते","m":"those"},{"d":"वनौकसः","m":"forest rangers"},{"d":"निवृत्य","m":"turning back"},{"d":"सङ्कृद्दाः","m":"to hit"},{"d":"परमक्रुद्धाः","m":"extremely angry"},{"d":"समदाः","m":"who were determined"},{"d":"कुञ्चराःइव","m":"like elephants in rut"},{"d":"कुम्भकर्णम्","m":"at Kumbhakarna"},{"d":"निर्जघ्नुः","m":"to vanquish him."}]},{"v":10,"dev":"प्रांशुभिर्गिरिशृङ्गैश्चशिलाभिश्चमहाबलः ।पादपैःपुष्पिताग्रैश्चहन्यमानो न कम्पते","trans":"Though Kumbhakarna was hit with lofty mountain peaks and trees with blossoms at crests, he was not shaken.","words":[{"d":"शुभिः","m":"lofty"},{"d":"गिरिशृङ्गैश्च","m":"mountain peaks"},{"d":"शिलाभिश्च","m":"rocks also"},{"d":"पुष्टिताग्रैः","m":"trees with blossoms on top tops"},{"d":"पादपैः","m":"trees"},{"d":"हन्यमानः","m":"though hit"},{"d":"महाबलः","m":"Kumbhakarna"},{"d":"न कम्पते","m":"not shaken."}]},{"v":11,"dev":"तस्यगात्रेषुपतिताभिद्यन्तेशतशश्शिलाः ।पादपाःपुष्पिताग्राश्चभग्नाःपेतुर्महीतले","trans":"Fallen on his limbs many rocks got broken, even the treetops with blossoms were broken and fell on the ground.","words":[{"d":"तस्य","m":"his"},{"d":"गात्रेषु","m":"limbs"},{"d":"बहवः","m":"many"},{"d":"शिलाः","m":"rocks"},{"d":"भिद्यन्ते","m":"were broken"},{"d":"पुष्पिताग्राश्च","m":"even the treetops with blossoms"},{"d":"पादपाः","m":"trees"},{"d":"भग्नाः","m":"broken"},{"d":"महीतले","m":"fell on the ground"},{"d":"पेतुः","m":"shattered."}]},{"v":12,"dev":"सोऽपिसैन्यानिसङ्क्रुद्धोवानराणांमहौजसाम् ।ममन्थपरमायत्तोवनान्यग्निरिवोत्थितः","trans":"Enraged Kumbhakarna began to destroy Vanaras endowed with extraordinary vigour, just as great forest fire burns the forest.","words":[{"d":"सःअपि","m":"he also"},{"d":"सङ्क्रुद्धः","m":"enraged"},{"d":"परमायत्तः","m":"the great"},{"d":"उत्थितः","m":"burst"},{"d":"अग्नि:","m":"fire"},{"d":"वनानीव","m":"forest"},{"d":"महौजसाम्","m":"endowed with extraordinary vigour"},{"d":"वानराणाम्","m":"Vanaras"},{"d":"सैन्यानि","m":"army"},{"d":"ममन्थ","m":"to destroy."}]},{"v":13,"dev":"लोहितार्द्रास्तुबहवश्शेरतेवानरर्षभाः ।निरस्तांपतिताभूमौताम्रपुष्पाइवद्रुमाः","trans":"Many bulls among the Vanaras lay on the ground like trees with red flowers on top tossed and fallen on the ground.","words":[{"d":"बहवः","m":"many"},{"d":"वानरर्षभाः","m":"bulls among Vanaras"},{"d":"लोहितार्द्रा:","m":"trees with red flowers on top"},{"d":"निरस्ताः","m":"tossed"},{"d":"भूमौ","m":"on the ground"},{"d":"पतिताः","m":"fallen"},{"d":"ताम्रपुष्पाः","m":"red flowers"},{"d":"द्रुमाःयथा","m":"like trees lay in blood."}]},{"v":14,"dev":"लङ्घयन्तःप्रधावन्तोवानरानावलोकयन् ।केचित्समुद्रेपतिताःकेचिद्गगनमास्थिताः","trans":"The Vanaras leapt without looking back. Indeed, some dropped into the ocean, and some flew into space.","words":[{"d":"वानराः","m":"Vanaras"},{"d":"लङ्घयन्तः","m":"leaping"},{"d":"प्रधावन्तः","m":"flying"},{"d":"नावलोकयन्","m":"not turning back to see"},{"d":"केचित्","m":"indeed"},{"d":"समुद्रे","m":"ocean"},{"d":"पतिताः","m":"dropped"},{"d":"केचित्","m":"some"},{"d":"गगनम्","m":"space"},{"d":"आस्थिताः","m":"flew."}]},{"v":15,"dev":"वध्यमानास्तुतेवीराराक्षसेन च लीलया ।सागरंयेनतेतीर्णाःपथातेनदुद्रुवुः","trans":"Struck by Rakshasa, the Vanaras ran in the same path crossing the ocean (by which they came).","words":[{"d":"राक्षसेन","m":"by Rakshasas"},{"d":"लीलया","m":"struck by"},{"d":"वध्यमानाः","m":"struck by"},{"d":"तेवीराः","m":"those heroes"},{"d":"येनपथा","m":"by the path"},{"d":"सागरम्","m":"ocean"},{"d":"तीर्णाः","m":"crossed"},{"d":"पथातेन","m":"by the same path"},{"d":"दुद्रुवुः","m":"ran."}]},{"v":16,"dev":"तेस्थलानितदानिम्नंविवर्णमानाभयात् ।ऋक्षावृक्षान् समारूढाःकेचित्पर्वतमाश्रिताः","trans":"Out of fear the vanaras rushed to plains with pale countenance, some climbed up mountains and bears climbed up trees.","words":[{"d":"तदा","m":"then"},{"d":"भयात्","m":"out of fear"},{"d":"विवर्णवदनाः","m":"pale countenance"},{"d":"ते","m":"they"},{"d":"स्थलानि","m":"location"},{"d":"निम्नम्","m":"plains"},{"d":"ऋक्षाः","m":"Bears"},{"d":"वृक्षान्","m":"trees"},{"d":"समारूढाः","m":"climbed up"},{"d":"केचित्","m":"some"},{"d":"पर्वतम्","m":"mountains"},{"d":"आश्रिताः","m":"sought resort."}]},{"v":17,"dev":"ममज्जुरर्णवेकेचिद्गुहाःकेचित्समाश्रिताः ।निपेतुःकेचिदपरेकेचिन्नैवावतस्थिरे केचिद्भूमौनिपतिताःकेचित्सुप्तामृताइव ।","trans":"Some drowned in the ocean, some entered into the caves, some others not knowing what to do sat down and others fell on the ground and some slept as if dead.","words":[{"d":"केचित्","m":"some"},{"d":"अर्णवे","m":"ocean"},{"d":"ममज्जुः","m":"drowned"},{"d":"केचित्","m":"some"},{"d":"गुहाः","m":"caves"},{"d":"समाश्रिताः","m":"took shelter"},{"d":"अपरेकेचित्","m":"and some others"},{"d":"निपेतुः","m":"not knowing anything"},{"d":"केचित्","m":"some"},{"d":"नैवअवतस्थिरे","m":"sat down"},{"d":"केचित्","m":"some"},{"d":"भूमौ","m":"on the ground"},{"d":"निपतिताः","m":"fallen"},{"d":"केचित्","m":"some"},{"d":"मृताः इव","m":"as if deadसुप्ताः slept."}]},{"v":18,"dev":"तान्समीक्ष्याङ्गदोभग्नान्वानरानिदमब्रवीत् अवतिष्ठतयुध्यामोनिवर्तध्वंप्लवङ्गमाः ।","trans":"Seeing the monkeys routed, Angada spoke, 'Stay, return back. We will fight'","words":[{"d":"भग्नान्","m":"routed"},{"d":"तान्","m":"them"},{"d":"वानरान्","m":"Vanaras"},{"d":"समीक्ष्य","m":"observing"},{"d":"इदम्","m":"thus"},{"d":"अब्रवीत्","m":"spoke"},{"d":"प्लवङ्गमाः","m":"to the monkeys"},{"d":"अवतिष्ठत","m":"stay"},{"d":"निवर्तध्वम्","m":"return"},{"d":"युध्यामः","m":"will fight."}]},{"v":19,"dev":"भग्नानांवो न पश्यामिपरिगम्यमहीमिमाम् स्थानंसर्वेनिवर्तध्वंकिंप्राणान् परिरक्षथ ।","trans":"\"I do not see any refuge for you even if you go round the globe. All of you return back. Why do you preserve life?\"","words":[{"d":"इमाम्","m":"this"},{"d":"महीम्","m":"globe"},{"d":"परिक्रम्य","m":"go round"},{"d":"भग्नानाम्","m":"routed"},{"d":"वः","m":"or"},{"d":"स्थानम्","m":"place"},{"d":"न पश्यामि","m":"not see"},{"d":"सर्वे","m":"all"},{"d":"निवर्तध्वम्","m":"return"},{"d":"प्राणान्","m":"life"},{"d":"किम्","m":"why"},{"d":"परिरक्षथ","m":"refuge."}]},{"v":20,"dev":"निरायुधानांद्रवतामसङ्गगतिपौरुषाः दाराह्युपहसिष्यन्ति स वैघातस्तुजीवताम् ।","trans":"\"Monkeys! Your valour can't be challenged. If you run away for life abandoning weapons even your wives will ridicule you. That is more than death.\"","words":[{"d":"असङ्गगतिपौरुषाः","m":"whose valour can't be challenged"},{"d":"निरायुधानाम्","m":"abandoning weapons"},{"d":"द्रवताम्","m":"run away"},{"d":"दाराः","m":"wives"},{"d":"उपहसिष्यन्ति","m":"will ridicule"},{"d":"जीवताम्","m":"life"},{"d":"सः","m":"for those"},{"d":"घातःवै","m":"indeed more than death."}]},{"v":21,"dev":"कुलेषुजातास्सर्वेस्मविस्तीर्णेषुमहत्सु च क्वगच्छतभयत्रस्ताःहरयःप्राकृतायथा ।अनार्याःखलुयद्भीतास्त्यक्त्वावीर्यंप्रधावत","trans":"\"You are born in noble families, and are widely spread. As such why are you running away like ordinary monkeys as if terrified giving up your valour. It is not worthy of you.\"","words":[{"d":"सर्वे","m":"all"},{"d":"विस्तीर्णेषु","m":"widely spread"},{"d":"महत्सु च","m":"noble also"},{"d":"कुलेषु","m":"clan"},{"d":"जाताःस्म","m":"born into"},{"d":"प्राकृताः","m":"ordinary"},{"d":"हरयःयथा","m":"monkeys like"},{"d":"भयत्रस्ताः","m":"in fear"},{"d":"क्व","m":"why"},{"d":"गच्छत","m":"go"},{"d":"वीर्यम्","m":"valour"},{"d":"त्यक्त्वा","m":"giving up"},{"d":"भीताः","m":"terrified"},{"d":"यत्","m":"as if"},{"d":"प्रधावत","m":"running away"},{"d":"अनार्याःखलु","m":"not worthy of."}]},{"v":22,"dev":"कुलेषुजातास्सर्वेस्मविस्तीर्णेषुमहत्सु च क्वगच्छतभयत्रस्ताःहरयःप्राकृतायथा ।अनार्याःखलुयद्भीतास्त्यक्त्वावीर्यंप्रधावत","trans":"\"You are born in noble families, and are widely spread. As such why are you running away like ordinary monkeys as if terrified giving up your valour. It is not worthy of you.\"","words":[{"d":"सर्वे","m":"all"},{"d":"विस्तीर्णेषु","m":"widely spread"},{"d":"महत्सु च","m":"noble also"},{"d":"कुलेषु","m":"clan"},{"d":"जाताःस्म","m":"born into"},{"d":"प्राकृताः","m":"ordinary"},{"d":"हरयःयथा","m":"monkeys like"},{"d":"भयत्रस्ताः","m":"in fear"},{"d":"क्व","m":"why"},{"d":"गच्छत","m":"go"},{"d":"वीर्यम्","m":"valour"},{"d":"त्यक्त्वा","m":"giving up"},{"d":"भीताः","m":"terrified"},{"d":"यत्","m":"as if"},{"d":"प्रधावत","m":"running away"},{"d":"अनार्याःखलु","m":"not worthy of."}]},{"v":23,"dev":"विकत्थनानिवोयानि तदावैजनसंसदि ।तानिवःक्वनुयातानिसोदग्राणिम हितानि च","trans":"\"Earlier in the assembly of people you made vigorous statements and acclaimed yourselves highly with selfpraise. Where has it gone?\"","words":[{"d":"यानि","m":"earlier"},{"d":"जनसंसदि","m":"in assembly of people"},{"d":"वः","m":"or else"},{"d":"सोदग्राणि","m":"made vigorous statements"},{"d":"महान्ति च","m":"acclaimed highly"},{"d":"यातानि","m":"such you"},{"d":"विकत्थनानि","m":"selfpraise"},{"d":"वः","m":"such you, all that"},{"d":"क्व","m":"where"},{"d":"गतानि","m":"has it gone."}]},{"v":24,"dev":"भीरुप्रवादाश्श्रूयन्तेयस्तुजीवतिधिक्कृतः ।मार्गस्सत्पुरुषैर्जष्टःसेव्यतांत्यज्यतांभयम्","trans":"\"He who is defeated lives, but people will say he is timid. Resorting to the path of good people and serving them gives up fear.\"","words":[{"d":"यः","m":"he who"},{"d":"धिक्कृतः","m":"having been defeated"},{"d":"जीवति","m":"lives"},{"d":"भीरोः","m":"timid"},{"d":"प्रवादाः","m":"will say"},{"d":"श्रूयन्ते","m":"will tell"},{"d":"सत्पुरुषैः","m":"good people"},{"d":"जुष्टः","m":"resorting to"},{"d":"मार्गः","m":"path"},{"d":"सेव्यताम्","m":"following"},{"d":"भयम्","m":"fear"},{"d":"त्यज्यताम्","m":"giving up."}]},{"v":25,"dev":"शयामहेऽनिहताःपृथिव्यामल्पजीविताः ।दुष्प्रापंब्रह्मलोकंवाप्राप्नुयामोयुधिसूदिता","trans":"\"If we are killed in war, fallen dead on the ground and our life span is reduced, we will attain the realm of Brahma which is difficult to attain.\"","words":[{"d":"अल्पजीविताः","m":"life span is reduced"},{"d":"निहताः","m":"having been killed"},{"d":"पृथिव्याम्","m":"in the world"},{"d":"युधिसूदिता","m":"killed in war"},{"d":"दुष्प्रापम्","m":"difficult to attain"},{"d":"ब्रह्मलोकम्","m":"world of Brahma"},{"d":"प्राप्नुयामः च","m":"will attain."}]},{"v":26,"dev":"सम्प्राप्नुयामःकीर्तिंवानिहत्वाशत्रुमाहवे ।जीवितंवीरलोकस्यमोक्ष्यामोवसुवानराः","trans":"\"By killing the enemy, we will attain fame. Or else we will attain the world of Brahma, liberated.\"","words":[{"d":"वानराः","m":"Vanara"},{"d":"आहवे","m":"we will"},{"d":"शत्रुम्","m":"the enemy"},{"d":"निहत्वा","m":"killing"},{"d":"कीर्तिम्","m":"fame"},{"d":"सम्प्राप्नुयामः","m":"will attain"},{"d":"वा","m":"or else"},{"d":"जीवितः","m":"life"},{"d":"वीरलोकस्य","m":"in the world of Brahma"},{"d":"वसु","m":"will be"},{"d":"मोक्ष्यामः","m":"liberated."}]},{"v":27,"dev":"न कुम्भकर्णःकाकुत्स्थंदृष्टवाजीवन् गमिष्यति ।दीप्यमानमिवासाद्यपतङ्गोज्वलनंयथा","trans":"\"Just as flies reaching the blazing fire can't escape, so also Kumbhakarna can't escape with life after facing Kakuthsa.\"","words":[{"d":"पतङ्गः","m":"fly"},{"d":"दीप्यमानम्","m":"reaching flame"},{"d":"ज्वलनम्","m":"blazing"},{"d":"आसाद्यइवयथा","m":"not possible to escape"},{"d":"कुम्भकर्णः","m":"for Kumbhakarna"},{"d":"काकुत्स्थम्","m":"Kakuthsa"},{"d":"दृष्टवा","m":"seeing"},{"d":"जीवन्","m":"life"},{"d":"न गच्छति","m":"not escape."}]},{"v":28,"dev":"लायनेनचोद्धिष्टाःप्राणान् रक्षामहेवयम् ।एकेनबहवोभग्नायशोनाशंगमिष्यति","trans":"\"Even though we are distinguished, if we preserve our life by running away for life, destroyed by one, our glory will come to an end.\"","words":[{"d":"एकेन","m":"by one"},{"d":"भग्नाः","m":"destroyed"},{"d":"बहवः","m":"though many"},{"d":"उददिष्टाः","m":"distinguished"},{"d":"वयम्","m":"we"},{"d":"पलायनने","m":"by running away"},{"d":"प्राणान्","m":"life"},{"d":"रक्षामहे","m":"protect"},{"d":"यशः","m":"glory"},{"d":"नाशम्","m":"gone"},{"d":"गमिष्यति","m":"come to an end."}]},{"v":29,"dev":"एवंब्रुवाणंतंशूरमङ्गदंकनकाङ्गदम् ।द्रवमाणास्ततोवाक्यमूचुःशूरुविगर्हितम्","trans":"While the heroic Angada, adorned with gold armlets, was speaking in that manner to the fleeing vanara heroes, condemned by the hero the vanaras replied as follows.","words":[{"d":"द्रवमाणाः","m":"fleeing away"},{"d":"एवम्","m":"in that manner"},{"d":"ब्रुवाणम्","m":"speaking"},{"d":"कनकाङ्गदम्","m":"adorned with gold armlets"},{"d":"शूरम्","m":"to the heroes"},{"d":"तम्","m":"that"},{"d":"अङ्गदम्","m":"Angada"},{"d":"ततः","m":"thereafter"},{"d":"शूरुविगर्हितम्","m":"condemned by hero"},{"d":"वाक्यम्","m":"words"},{"d":"ऊचुः","m":"said."}]},{"v":30,"dev":"कृतंनःकदनंघोरंकुम्भकर्णेनरक्षसा ।न स्थानकालोगच्छामोदयितंजीवितंहिनः","trans":"\"Kumbhakarna, the Rakshasa has done havoc to us. This is not the moment to stay. Our life is dear to us.\"","words":[{"d":"नः","m":"us"},{"d":"रक्षसा","m":"Rakshasa"},{"d":"घोरम्","m":"dreadful"},{"d":"कदनम्","m":"havoc"},{"d":"कृतम्","m":"done"},{"d":"स्थानकालः","m":"moment to stay"},{"d":"न","m":"not"},{"d":"नः","m":"we"},{"d":"जीवितम्","m":"our life"},{"d":"दयितंहि","m":"dear to us."}]},{"v":31,"dev":"एतावदुक्त्वावचनंसर्वेतेभेजिरेदिशः ।भीमंभीमाक्षमायान्तंदृष्टवावानरयूथपाः","trans":"All the Vanara troops having replied that way, seeing Kumbhakarna of frightful eyes coming towards them, scattered in all directions.","words":[{"d":"सर्वे","m":"all,एता to you. वानरयूथपाः Vanara troops"},{"d":"भीमाक्षम्","m":"frightful eyes"},{"d":"भीमम्","m":"fear"},{"d":"आयान्तम्","m":"coming towards"},{"d":"दृष्टवा","m":"seeing"},{"d":"एतावत्","m":"in that way"},{"d":"उक्त्वा","m":"having spoken"},{"d":"दिशः","m":"directions"},{"d":"भेजिरे","m":"scattered."}]},{"v":32,"dev":"द्रवमाणस्तुतेवीराअङ्गदेनवलीमुखाः ।सान्त्वैश्चैहनुमानैश्चततस्सर्वेनिवर्तिताः","trans":"Though the heroic monkeys were running away, Angada by his good words and examples turned them to return from wherever they were.","words":[{"d":"द्रवमाणाः","m":"running away"},{"d":"वीराः","m":"heroes"},{"d":"ते","m":"you are"},{"d":"वलीमुखाः","m":"to return back"},{"d":"सरेततः","m":"wherever they were"},{"d":"अङ्गदेन","m":"by Angada"},{"d":"सान्त्वैश्चै","m":"with good words"},{"d":"अनुमानैश्च","m":"by examples"},{"d":"निवर्तिताः","m":"turned."}]},{"v":33,"dev":"प्रहर्षमुपनीताश्चवालिपुत्रेणधीमता ।आज्ञाप्रतीक्षास्तस्थुश्चसर्वेवानरयूथपाः","trans":"All the Vanara troops having heard Angada, son of Vali happily restored awaiting his command.","words":[{"d":"सर्वे","m":"all"},{"d":"वानरयूथपाः","m":"Vanara troops"},{"d":"धीमता","m":"wise"},{"d":"वालिपुत्रेण","m":"Vali's son"},{"d":"प्रहर्षम्","m":"happily"},{"d":"उपनीताः च","m":"restored"},{"d":"आज्ञाप्रतीक्षाः","m":"awaiting command"},{"d":"तस्थुः च","m":"stood"}]},{"v":34,"dev":"ऋषभशरभमैन्दधूम्रनीलाःकुमुदसुषेणगवाक्षरम्भताराः ।द्विविदपनसवायुपुत्रमुख्यास्त्वरिततराभिमुखंरणं","trans":"Rshaba, Sarabha, Mainda and Nila, Kumuda, Susena, Rambha, and Tara headed by Dwiviida, Panasa and Hanuman marched ahead swiftly to the battlefield. ।। इत्यार्षेवाल्मीकीयेश्रीमद्रामायणेआदिकाव्येयुद्धकाण्डेषष्टितमस्सर्गः ।। This is the end of the sixty sixth sarga of Yuddha Kanda of the first epic, the holy Ramayana composed by sage Valmiki.","words":[{"d":"ऋषभशरभमैन्धधूम्रनीलाः","m":"Rshaba, Sarabha, Mainda, Dhruma and Nila"},{"d":"कुमुदसुषेणगवाक्षम्भताराः","m":"Kumuda, Susena, Gavaksha, Rambha, and Tara"},{"d":"द्विविदपनसवायुपुत्रमुख्याः","m":"Dwivida, Panasa, and Hanuman"},{"d":"त्वरिततराभिमुखम्","m":"marched ahead swiftly"},{"d":"रणम्","m":"to the battlefield"},{"d":"प्रयाताः","m":"quickly."}]}]}